movie_search/__init__.py
movie_search/__main__.py
movie_search/__version__.py
movie_search/api.py
movie_search/movie.py
movie_search/utils.py
movie_search/sources/__init__.py
movie_search/sources/douban.py
test/__init__.py
test/test.py
movie_search-0.0.2.dist-info/METADATA
movie_search-0.0.2.dist-info/WHEEL
movie_search-0.0.2.dist-info/entry_points.txt
movie_search-0.0.2.dist-info/top_level.txt
movie_search-0.0.2.dist-info/RECORD
